cli/cli.py
discordpy_bot_cli-7.0.dist-info/LICENSE
discordpy_bot_cli-7.0.dist-info/METADATA
discordpy_bot_cli-7.0.dist-info/WHEEL
discordpy_bot_cli-7.0.dist-info/entry_points.txt
discordpy_bot_cli-7.0.dist-info/top_level.txt
discordpy_bot_cli-7.0.dist-info/RECORD
