Metadata-Version: 2.1
Name: discordpy-bot-cli
Version: 7.0
Summary: CLI for helping in making Discord bots easily
Home-page: UNKNOWN
Author: Areen Rath
License: UNKNOWN
Platform: UNKNOWN
Classifier: Programming Language :: Python :: 3
Classifier: License :: OSI Approved :: MIT License
Classifier: Operating System :: OS Independent
Requires-Python: >=3.6
License-File: LICENSE
